cjax/__init__.py
cjax/continuation/__init__.py
cjax/continuation/_arc_len_continuation.py
cjax/continuation/_perturbed_arc_len_continuation.py
cjax/continuation/base_continuation.py
cjax/continuation/natural_continuation.py
cjax/continuation/perturbed_fixed_arclen_continuation.py
cjax/continuation/secant_continuation.py
cjax/continuation/creator/__init__.py
cjax/continuation/creator/continuation_creator.py
cjax/continuation/methods/__init__.py
cjax/continuation/methods/corrector/__init__.py
cjax/continuation/methods/corrector/_perturb_parc_evolve.py
cjax/continuation/methods/corrector/base_corrector.py
cjax/continuation/methods/corrector/constrained_corrector.py
cjax/continuation/methods/corrector/perturb_parc_evolve.py
cjax/continuation/methods/corrector/perturbed_constrained_corrector.py
cjax/continuation/methods/corrector/perturbed_constrained_fixed_corrector.py
cjax/continuation/methods/corrector/unconstrained_corrector.py
cjax/continuation/methods/predictor/__init__.py
cjax/continuation/methods/predictor/arc_secant_predictor.py
cjax/continuation/methods/predictor/base_predictor.py
cjax/continuation/methods/predictor/natural_predictor.py
cjax/continuation/methods/predictor/secant_predictor.py
cjax/continuation/states/__init__.py
cjax/continuation/states/state_variables.py
cjax/optimizer/__init__.py
cjax/optimizer/optimizer.py
cjax/utils/__init__.py
cjax/utils/abstract_problem.py
cjax/utils/custom_nn.py
cjax/utils/data_batch_sizer.py
cjax/utils/data_img_gamma.py
cjax/utils/dataset_conv.py
cjax/utils/datasets.py
cjax/utils/eval.py
cjax/utils/evolve_utils.py
cjax/utils/math_trees.py
cjax/utils/minima_dist.py
cjax/utils/neted_jit_test.py
cjax/utils/profiler.py
cjax/utils/random_network_data_pair.py
cjax/utils/rotation_ndims.py
cjax/utils/rotation_ndims_numpy.py
cjax/utils/visualizer.py
examples/__init__.py
examples/torch_data.py
examples/autoencoder/__init__.py
examples/autoencoder/autoencoder.py
examples/autoencoder/run.py
examples/conv_nn/__init__.py
continuation_jax-0.0.7.dist-info/LICENSE
continuation_jax-0.0.7.dist-info/METADATA
continuation_jax-0.0.7.dist-info/WHEEL
continuation_jax-0.0.7.dist-info/top_level.txt
continuation_jax-0.0.7.dist-info/RECORD
