Metadata-Version: 2.1
Name: continuation-jax
Version: 0.0.7
Summary: Continuation Methods for Deep Neural Networks.
Home-page: https://github.com/harsh306/continuation-jax
Author: Harsh Nilesh Pathak
Author-email: harshnpathak@gmail.com
License: UNKNOWN
Platform: UNKNOWN
Classifier: Programming Language :: Python :: 3
Classifier: License :: OSI Approved :: MIT License
Classifier: Operating System :: OS Independent
Classifier: Intended Audience :: Developers
Classifier: Intended Audience :: Science/Research
Classifier: Topic :: Scientific/Engineering :: Artificial Intelligence
Requires-Python: >=3.6
License-File: LICENSE
Requires-Dist: pandas (==1.1.3)
Requires-Dist: numpy (==1.19.2)
Requires-Dist: matplotlib (==3.3.2)
Requires-Dist: scipy (==1.5.2)
Requires-Dist: Sphinx (==3.2.1)
Requires-Dist: flax (==0.3.4)
Requires-Dist: jax (==0.2.14)
Requires-Dist: jsonlines (==2.0.0)
Requires-Dist: mlflow (==1.17.0)
Requires-Dist: sphinx-rtd-theme (==0.5.2)
Requires-Dist: torch (==1.8.1)
Requires-Dist: torchvision (==0.9.1)
